zeroslib_package/__init__.py
zeroslib_package/zeroslib.py
zeroslib-0.2.3.dist-info/LICENSE
zeroslib-0.2.3.dist-info/METADATA
zeroslib-0.2.3.dist-info/WHEEL
zeroslib-0.2.3.dist-info/top_level.txt
zeroslib-0.2.3.dist-info/RECORD
