Metadata-Version: 2.1
Name: zeroslib
Version: 0.2.3
Summary: A package
Home-page: https://github.com/pypa/sampleproject
Author: lucasz228
Author-email: github.io@qq.com
License: UNKNOWN
Project-URL: Bug Tracker, https://github.com/pypa/sampleproject/issues
Platform: UNKNOWN
Classifier: Programming Language :: Python :: 3
Classifier: License :: OSI Approved :: MIT License
Classifier: Operating System :: OS Independent
Requires-Python: >=3.6
License-File: LICENSE
